{
  "publicPath": "/_nuxt/",
  "all": [
    "../server/index.spa.html",
    "../server/index.ssr.html",
    "0124e6d9cbda5b8f4f7a.js",
    "018c9f2e095b1d95bd19.js",
    "3284f505200c9f2e610c.js",
    "390b2ea62831bc7a2637.js",
    "42c5424c08809fde9981.js",
    "493c5bc69af9618c8e37.js",
    "53ef975bc5a3293d71f2.js",
    "5421bb01bf9a602e339e.js",
    "643d6b219715096d7653.js",
    "67de9a93b4b9ff249ef0.js",
    "6d619c9e6d98b2169199.js",
    "75c65cb53e7620404371.js",
    "LICENSES",
    "a84f06bc21d67a5b8e44.js",
    "b1352a776b8a5e09c338.js",
    "c083b106638f907aea30.js",
    "e6f646850f1bcb4a1675.js"
  ],
  "initial": [
    "3284f505200c9f2e610c.js",
    "390b2ea62831bc7a2637.js",
    "6d619c9e6d98b2169199.js"
  ],
  "async": [
    "0124e6d9cbda5b8f4f7a.js",
    "018c9f2e095b1d95bd19.js",
    "42c5424c08809fde9981.js",
    "493c5bc69af9618c8e37.js",
    "53ef975bc5a3293d71f2.js",
    "5421bb01bf9a602e339e.js",
    "643d6b219715096d7653.js",
    "67de9a93b4b9ff249ef0.js",
    "75c65cb53e7620404371.js",
    "a84f06bc21d67a5b8e44.js",
    "b1352a776b8a5e09c338.js",
    "c083b106638f907aea30.js",
    "e6f646850f1bcb4a1675.js"
  ],
  "modules": {
    "14826625": [
      5
    ],
    "15689865": [
      18
    ],
    "25468299": [
      5
    ],
    "28044463": [
      6
    ],
    "31317017": [
      10
    ],
    "31388960": [
      5
    ],
    "34378230": [
      5
    ],
    "46431336": [
      5
    ],
    "58276976": [
      18
    ],
    "73567130": [
      7
    ],
    "73912076": [
      5
    ],
    "74370082": [
      7
    ],
    "75187892": [
      7
    ],
    "75950640": [
      7
    ],
    "86957444": [
      6
    ],
    "6c8f8d6c": [
      12
    ],
    "7633896c": [
      5
    ],
    "018957ab": [
      5
    ],
    "75ed0c61": [
      5
    ],
    "104b54ab": [
      5
    ],
    "77fab6b0": [
      5
    ],
    "332473c6": [
      5
    ],
    "4394e251": [
      5
    ],
    "0579fdd0": [
      5
    ],
    "8007ab96": [
      5
    ],
    "364ffd68": [
      5
    ],
    "11ff31a2": [
      5
    ],
    "25b03531": [
      5
    ],
    "4e5a310e": [
      5
    ],
    "b647bcee": [
      12
    ],
    "30e60cea": [
      12
    ],
    "09f3a41c": [
      12
    ],
    "084fed60": [
      12
    ],
    "1d4b8bf0": [
      12
    ],
    "73de96bf": [
      12
    ],
    "65331efa": [
      12
    ],
    "fa4f5a5c": [
      12
    ],
    "032a4fa6": [
      12
    ],
    "6eef4d24": [
      12
    ],
    "6315d014": [
      12
    ],
    "fd570510": [
      12
    ],
    "d27ffcb0": [
      12
    ],
    "640d40b2": [
      12
    ],
    "400a0520": [
      12
    ],
    "68fe7a34": [
      12
    ],
    "6204c6d4": [
      12
    ],
    "5ecc4c1f": [
      5
    ],
    "3e3e3401": [
      5
    ],
    "1ac7c3b0": [
      5
    ],
    "40ca3f20": [
      5
    ],
    "ebbb7f1c": [
      5
    ],
    "b56d0dc6": [
      5
    ],
    "01b4519c": [
      5
    ],
    "7aee2cca": [
      5
    ],
    "02f0b8f8": [
      5
    ],
    "58c0980f": [
      5
    ],
    "fc7c1f7e": [
      5
    ],
    "0406b44c": [
      5
    ],
    "402cf6ba": [
      5
    ],
    "99d97bf6": [
      5
    ],
    "375f4d79": [
      5
    ],
    "56b85366": [
      5
    ],
    "0d9b0a13": [
      5
    ],
    "3a8ee6b5": [
      5
    ],
    "52be7b19": [
      5
    ],
    "bc3c94c4": [
      5
    ],
    "b0d519a4": [
      5
    ],
    "0088945f": [
      5
    ],
    "2545fe20": [
      5
    ],
    "e346f6f6": [
      5
    ],
    "2f94d3d1": [
      5
    ],
    "841544b4": [
      5
    ],
    "2f928df6": [
      5
    ],
    "5ae531ca": [
      5
    ],
    "6a824afb": [
      5
    ],
    "28e7edf2": [
      5
    ],
    "101908fa": [
      5
    ],
    "4ea627a6": [
      5
    ],
    "00b3a081": [
      12
    ],
    "134b738d": [
      12
    ],
    "66d09f8d": [
      12
    ],
    "21942ea2": [
      5
    ],
    "4ad879c6": [
      5
    ],
    "d8304622": [
      5
    ],
    "739a5c0d": [
      5
    ],
    "3499be5e": [
      5
    ],
    "2f8e0240": [
      5
    ],
    "16058d03": [
      5
    ],
    "30f88396": [
      5
    ],
    "e5978944": [
      5
    ],
    "59910a70": [
      5
    ],
    "58c4febe": [
      5
    ],
    "08ec5f62": [
      5
    ],
    "5985a7fe": [
      12
    ],
    "7d724c20": [
      5
    ],
    "27d50757": [
      12
    ],
    "3fa96180": [
      12
    ],
    "75a814a5": [
      12
    ],
    "48a8cb3e": [
      5
    ],
    "5685e01b": [
      5
    ],
    "7e16ddcc": [
      5
    ],
    "6bb6a60d": [
      5
    ],
    "237c58e0": [
      5
    ],
    "1c36f2bc": [
      5
    ],
    "544ac0c2": [
      5
    ],
    "32f967c5": [
      5
    ],
    "5df6ce93": [
      5
    ],
    "7cf0749b": [
      5
    ],
    "a9060352": [
      5
    ],
    "277759e6": [
      5
    ],
    "23a0c3ca": [
      5
    ],
    "057a4c7e": [
      5
    ],
    "5babd911": [
      5
    ],
    "4676fad6": [
      5
    ],
    "b59a2cbc": [
      5
    ],
    "7ff94e7f": [
      5
    ],
    "0555c1a6": [
      5
    ],
    "0bd48cb9": [
      5
    ],
    "60249bb6": [
      5
    ],
    "1000e77a": [
      12
    ],
    "530b08ea": [
      5
    ],
    "1cfa7e1e": [
      12
    ],
    "7705a17b": [
      5
    ],
    "7c1adfae": [
      12
    ],
    "95476db0": [
      12
    ],
    "12318e94": [
      5
    ],
    "30e6f639": [
      5
    ],
    "ac37902a": [
      5
    ],
    "7b95759c": [
      5
    ],
    "a1fe1f68": [
      5
    ],
    "148a9dff": [
      5
    ],
    "6fae5eaa": [
      5
    ],
    "757cb7ee": [
      5
    ],
    "abc7d1bc": [
      5
    ],
    "438dc7b3": [
      5
    ],
    "6c3f95e9": [
      5
    ],
    "7aafa8e0": [
      5
    ],
    "3dffa864": [
      5
    ],
    "0754da56": [
      5
    ],
    "5e508ba9": [
      5
    ],
    "045ebdd2": [
      5
    ],
    "409f610a": [
      5
    ],
    "060268f1": [
      5
    ],
    "1186c128": [
      5
    ],
    "19ea5701": [
      5
    ],
    "1809e8ae": [
      5
    ],
    "44a26701": [
      5
    ],
    "3707dce2": [
      5
    ],
    "c3b7899c": [
      5
    ],
    "53e59bea": [
      5
    ],
    "545f900d": [
      5
    ],
    "66f8fd78": [
      5
    ],
    "6f12cc2e": [
      5
    ],
    "9d387338": [
      5
    ],
    "41af3250": [
      5
    ],
    "5975ed60": [
      5
    ],
    "7fb6d79e": [
      5
    ],
    "3e76f233": [
      5
    ],
    "7c2010b2": [
      5
    ],
    "14c50bc3": [
      5
    ],
    "2aced8a2": [
      5
    ],
    "a6bf11a0": [
      5
    ],
    "e595f6e6": [
      5
    ],
    "4cf87c0d": [
      5
    ],
    "462b27fc": [
      5
    ],
    "70ea9ada": [
      5
    ],
    "5d758394": [
      5
    ],
    "db4eaa98": [
      5
    ],
    "d9306ada": [
      12
    ],
    "9e91197e": [
      12
    ],
    "6cc53dc2": [
      12
    ],
    "5cb4d366": [
      12
    ],
    "3df86db4": [
      7
    ],
    "3a9894f5": [
      6
    ],
    "44fa880f": [
      18
    ],
    "db84d338": [
      18
    ],
    "14f1977e": [
      18
    ],
    "3c2e13a3": [
      18
    ],
    "66d34f7a": [
      18
    ],
    "14aa8a42": [
      18
    ],
    "8bf4299e": [
      18
    ],
    "0de49ef9": [
      18
    ],
    "8200d122": [
      18
    ],
    "6da21c7a": [
      18
    ],
    "03ca1a73": [
      18
    ],
    "5e7eea9a": [
      18
    ],
    "acfb85e6": [
      18
    ],
    "2c5ae350": [
      18
    ],
    "6a1d5e5b": [
      11
    ],
    "6a946df1": [
      17
    ],
    "d72fc74a": [
      18
    ],
    "0850758f": [
      18
    ],
    "ace1fdf4": [
      18
    ],
    "a1c6460a": [
      13
    ],
    "0c5930c1": [
      3
    ],
    "c38d97ce": [
      8
    ],
    "379c324c": [
      2
    ],
    "ff927ece": [
      2
    ],
    "2d765557": [
      2
    ],
    "7d2bbf32": [
      2
    ],
    "279a1e21": [
      2
    ],
    "52ec5f47": [
      2
    ],
    "1b0f5ca2": [
      2
    ],
    "7ef3036a": [
      6
    ],
    "382962e1": [
      6
    ],
    "3d3c8cfd": [
      6
    ],
    "26a585ad": [
      6
    ],
    "4f4d22b6": [
      6
    ],
    "f363571e": [
      6
    ],
    "0430c7cc": [
      6
    ],
    "674cba17": [
      6
    ],
    "758a1d58": [
      7
    ],
    "3797bdd2": [
      7
    ],
    "36d52efe": [
      7
    ],
    "36b72e80": [
      7
    ],
    "36b0d14e": [
      7
    ],
    "3607b742": [
      7
    ],
    "35dfb69a": [
      7
    ],
    "7582d768": [
      7
    ],
    "7579bffc": [
      7
    ],
    "7577ee80": [
      7
    ],
    "75727a0c": [
      7
    ],
    "7571914e": [
      7
    ],
    "7570a890": [
      7
    ],
    "756dee56": [
      7
    ],
    "756d0598": [
      7
    ],
    "756133f2": [
      7
    ],
    "7550d696": [
      7
    ],
    "754e1c5c": [
      7
    ],
    "754b6222": [
      7
    ],
    "754504f0": [
      7
    ],
    "754161f8": [
      7
    ],
    "6bf9a4aa": [
      7
    ],
    "6c105f38": [
      7
    ],
    "7531ed5a": [
      7
    ],
    "751ed5c4": [
      7
    ],
    "a1cdadde": [
      7
    ],
    "a019499e": [
      7
    ],
    "9ff31a72": [
      7
    ],
    "9f8175ac": [
      7
    ],
    "9f465d6e": [
      7
    ],
    "9f40003c": [
      7
    ],
    "9ea65ace": [
      7
    ],
    "751c1b8a": [
      7
    ],
    "8ecbe082": [
      7
    ],
    "8ce91e68": [
      7
    ],
    "75178fd4": [
      7
    ],
    "7516a716": [
      7
    ],
    "750ca6ec": [
      7
    ],
    "750560fc": [
      7
    ],
    "74ffec88": [
      7
    ],
    "74fd324e": [
      7
    ],
    "28fee6ac": [
      7
    ],
    "28f8897a": [
      7
    ],
    "74f6d51c": [
      7
    ],
    "74f077ea": [
      7
    ],
    "74edbdb0": [
      7
    ],
    "74e677c0": [
      7
    ],
    "218cf64e": [
      7
    ],
    "74de4912": [
      7
    ],
    "74d0a5f0": [
      7
    ],
    "74cd02f8": [
      7
    ],
    "74c4d44a": [
      7
    ],
    "74c21a10": [
      7
    ],
    "2d77caa1": [
      7
    ],
    "74b55fac": [
      7
    ],
    "74a7bc8a": [
      7
    ],
    "74a6d3cc": [
      7
    ],
    "e6188f3c": [
      7
    ],
    "749beae4": [
      7
    ],
    "7488d34e": [
      7
    ],
    "747fbbe2": [
      7
    ],
    "7476a476": [
      7
    ],
    "7474d2fa": [
      7
    ],
    "7473ea3c": [
      7
    ],
    "7473017e": [
      7
    ],
    "746d8d0a": [
      7
    ],
    "7469ea12": [
      7
    ],
    "7462a422": [
      7
    ],
    "7456d27c": [
      7
    ],
    "745246c6": [
      7
    ],
    "7450754a": [
      7
    ],
    "7443bae6": [
      7
    ],
    "744017ee": [
      7
    ],
    "743e4672": [
      7
    ],
    "743d5db4": [
      7
    ],
    "743b8c38": [
      7
    ],
    "7437e940": [
      7
    ],
    "0fb25414": [
      7
    ],
    "743617c4": [
      7
    ],
    "74318c0e": [
      7
    ],
    "742a461e": [
      7
    ],
    "74278be4": [
      7
    ],
    "74212eb2": [
      7
    ],
    "25cf6bd2": [
      7
    ],
    "741f5d36": [
      7
    ],
    "775cd3e8": [
      7
    ],
    "73e8d0ae": [
      7
    ],
    "73e18abe": [
      7
    ],
    "641266b0": [
      7
    ],
    "73adb870": [
      7
    ],
    "73a843fc": [
      7
    ],
    "739b8998": [
      7
    ],
    "739aa0da": [
      7
    ],
    "7396fde2": [
      7
    ],
    "73952c66": [
      7
    ],
    "739443a8": [
      7
    ],
    "738fb7f2": [
      7
    ],
    "738ecf34": [
      7
    ],
    "bc056e2a": [
      7
    ],
    "738de676": [
      7
    ],
    "738b2c3c": [
      7
    ],
    "738a437e": [
      7
    ],
    "738214d0": [
      7
    ],
    "737e71d8": [
      7
    ],
    "01f70b86": [
      7
    ],
    "737ca05c": [
      7
    ],
    "737bb79e": [
      7
    ],
    "5d25fd7c": [
      7
    ],
    "02543b99": [
      7
    ],
    "7372a032": [
      7
    ],
    "031b5623": [
      7
    ],
    "031bca82": [
      7
    ],
    "3051e670": [
      7
    ],
    "8858ea7a": [
      7
    ],
    "735cce62": [
      7
    ],
    "734f2b40": [
      7
    ],
    "4016fd5c": [
      7
    ],
    "734270dc": [
      7
    ],
    "45bcf1dc": [
      7
    ],
    "72e86f62": [
      7
    ],
    "0fc0b342": [
      7
    ],
    "0f368272": [
      7
    ],
    "0dd96572": [
      7
    ],
    "11fc3f65": [
      11
    ],
    "2f3af099": [
      11
    ],
    "363043a7": [
      17
    ],
    "bb06c81a": [
      17
    ],
    "02e185de": [
      18
    ],
    "580b9b5d": [
      18
    ],
    "4038a391": [
      18
    ],
    "2670cc3c": [
      18
    ],
    "124ec788": [
      18
    ],
    "0e6a309e": [
      13
    ],
    "3b5a39fd": [
      13
    ],
    "0f27066a": [
      3
    ],
    "07c773ff": [
      3
    ],
    "c061357a": [
      8
    ],
    "1e7771e0": [
      6
    ],
    "053b9b86": [
      6
    ],
    "b91ce33c": [
      6
    ],
    "0f228fa4": [
      6
    ],
    "2e0296fc": [
      6
    ],
    "4664810b": [
      6
    ],
    "5889d86b": [
      6
    ],
    "5ecd281c": [
      6
    ],
    "99e6b9ea": [
      6
    ],
    "2f80b282": [
      6
    ],
    "44a2ad61": [
      6
    ],
    "6b8c27e2": [
      6
    ],
    "6099cfa6": [
      6
    ],
    "40de095e": [
      6
    ],
    "5b288c2b": [
      6
    ],
    "1b1aff4f": [
      8
    ],
    "06f8fa9b": [
      8
    ],
    "1def79d6": [
      2
    ],
    "2bb6000a": [
      2
    ],
    "3c2663ca": [
      2
    ],
    "1567609d": [
      2
    ],
    "c002542e": [
      2
    ],
    "714828d7": [
      2
    ],
    "985109ba": [
      2
    ],
    "074ba961": [
      7
    ],
    "584f7c3d": [
      2
    ],
    "a6ebc206": [
      2
    ],
    "d161296e": [
      2
    ],
    "133fbb54": [
      2
    ],
    "6987e4c4": [
      2
    ],
    "2c18222c": [
      2
    ],
    "1fd5f740": [
      2
    ],
    "496726da": [
      2
    ],
    "3ab86c74": [
      2
    ],
    "c5649c84": [
      2
    ],
    "590f7dc9": [
      2
    ],
    "79b520d0": [
      2
    ],
    "3c945aef": [
      2
    ],
    "17d934cc": [
      2
    ],
    "4a69d430": [
      2
    ],
    "008ca156": [
      2
    ],
    "4e1103fb": [
      2
    ],
    "5c4e9da5": [
      2
    ],
    "3d4c8bae": [
      2
    ],
    "47e01860": [
      2
    ],
    "a63f6642": [
      2
    ],
    "c8735a82": [
      2
    ],
    "58bd1f79": [
      2
    ],
    "7d60c24b": [
      2
    ],
    "29991bb0": [
      2
    ],
    "29f65f7a": [
      2
    ],
    "088daa1d": [
      2
    ],
    "62c2b34e": [
      2
    ],
    "37ddadb7": [
      2
    ],
    "4f533c51": [
      2
    ],
    "22255e32": [
      2
    ],
    "5c358210": [
      2
    ],
    "9c481552": [
      2
    ],
    "75feb031": [
      2
    ],
    "052d0925": [
      17
    ],
    "0e08f81d": [
      17
    ],
    "41309c8f": [
      17
    ],
    "eed8f492": [
      17
    ],
    "462a48cd": [
      17
    ],
    "c7cb2e92": [
      11
    ],
    "560e21e2": [
      11
    ],
    "2610e17f": [
      11
    ],
    "7808e396": [
      11
    ],
    "7f6685fe": [
      11
    ],
    "503ff766": [
      8
    ],
    "0d4b3bc5": [
      8
    ],
    "b9fb33b2": [
      8
    ],
    "871f3042": [
      8
    ],
    "2e5609e5": [
      8
    ],
    "4723eac6": [
      3
    ],
    "2da25980": [
      3
    ],
    "464f1dd9": [
      3
    ],
    "49e16f66": [
      3
    ],
    "604d685b": [
      3
    ],
    "aef4b210": [
      16
    ],
    "4c7913f9": [
      16
    ],
    "4329e31c": [
      16
    ],
    "7f516793": [
      16
    ],
    "224a715a": [
      16
    ],
    "38650c5c": [
      9
    ],
    "01791faf": [
      9
    ],
    "44c6907a": [
      9
    ],
    "29ab3f55": [
      9
    ],
    "49b7c9fc": [
      9
    ],
    "687a6c04": [
      15
    ],
    "0f29e06e": [
      15
    ],
    "3c23e5d0": [
      15
    ],
    "375c0014": [
      15
    ],
    "324172cc": [
      15
    ],
    "646e44af": [
      13
    ],
    "19ceaede": [
      13
    ],
    "5e7490c5": [
      13
    ],
    "55a220aa": [
      13
    ],
    "8bbc23fa": [
      13
    ],
    "41b852be": [
      10
    ],
    "7621bfde": [
      10
    ],
    "c4c883d6": [
      10
    ],
    "835e1d92": [
      10
    ]
  },
  "assetsMapping": {
    "0124e6d9cbda5b8f4f7a.js": "2a130dde",
    "018c9f2e095b1d95bd19.js": "10702230",
    "3284f505200c9f2e610c.js": "6fca0322",
    "390b2ea62831bc7a2637.js": "0859c165",
    "42c5424c08809fde9981.js": "4a652689",
    "493c5bc69af9618c8e37.js": "7e1e61ce",
    "53ef975bc5a3293d71f2.js": "53a5eeea",
    "5421bb01bf9a602e339e.js": "cc73e422",
    "643d6b219715096d7653.js": "1c535174",
    "67de9a93b4b9ff249ef0.js": "3ad7aa6c",
    "6d619c9e6d98b2169199.js": "1a3ae26b",
    "75c65cb53e7620404371.js": "34dc148c",
    "a84f06bc21d67a5b8e44.js": "c75026de",
    "b1352a776b8a5e09c338.js": "77e780d5",
    "c083b106638f907aea30.js": "589972fc",
    "e6f646850f1bcb4a1675.js": "0b6ac3b0"
  }
}